turbo_response/__init__.py
turbo_response/apps.py
turbo_response/cable_channel.py
turbo_response/channel_helper.py
turbo_response/constants.py
turbo_response/decorators.py
turbo_response/frame.py
turbo_response/middleware.py
turbo_response/mixins.py
turbo_response/renderers.py
turbo_response/response.py
turbo_response/shortcuts.py
turbo_response/stream.py
turbo_response/template.py
turbo_response/templatetags/__init__.py
turbo_response/templatetags/turbo_helper.py
turbo_response/views.py
django_turbo_response-1.0.3.dist-info/LICENSE
django_turbo_response-1.0.3.dist-info/METADATA
django_turbo_response-1.0.3.dist-info/WHEEL
django_turbo_response-1.0.3.dist-info/RECORD
